pyut2serverlist/__init__.py
pyut2serverlist/buffer.py
pyut2serverlist/connection.py
pyut2serverlist/constants.py
pyut2serverlist/exceptions.py
pyut2serverlist/filter.py
pyut2serverlist/logger.py
pyut2serverlist/packet.py
pyut2serverlist/principalserver.py
pyut2serverlist/server.py
pyut2serverlist-0.2.0.dist-info/LICENSE
pyut2serverlist-0.2.0.dist-info/METADATA
pyut2serverlist-0.2.0.dist-info/WHEEL
pyut2serverlist-0.2.0.dist-info/top_level.txt
pyut2serverlist-0.2.0.dist-info/RECORD
